pybsv/__init__.py
pybsv-0.0.5.dist-info/LICENSE
pybsv-0.0.5.dist-info/METADATA
pybsv-0.0.5.dist-info/WHEEL
pybsv-0.0.5.dist-info/top_level.txt
pybsv-0.0.5.dist-info/RECORD
