Metadata-Version: 2.1
Name: pybsv
Version: 0.0.5
Summary: An easy to use Python BSV client.
Home-page: http://github.com/jannainm/pybsv
Author: jannainm
Author-email: jannainm@gmail.com
License: MIT
Platform: UNKNOWN
Requires-Dist: bitsv (<1)
